{"2057":{"subject":"ARABIC","name":"1070A","type":"LEC","schedule":[{"start":"2021/9/13 8:30 AM","end":"2021/9/13 11:30 AM","rrule":{"byday":["MO"],"until":"2021/12/8","freq":"WEEKLY"},"location":"HC-A1"}],"instructor":"Y. Kharrat"},"3829":{"subject":"ARABIC","name":"1030","type":"LEC","schedule":[{"start":"2021/9/13 11:30 AM","end":"2021/9/13 1:30 PM","rrule":{"byday":["MO","WE"],"until":"2022/4/1","freq":"WEEKLY"},"location":"UCC-59"}],"instructor":"Y. Kharrat"},"6141":{"subject":"ARABIC","name":"1035","type":"LEC","schedule":[{"start":"2021/9/13 11:30 AM","end":"2021/9/13 1:30 PM","rrule":{"byday":["MO","WE"],"until":"2022/4/1","freq":"WEEKLY"},"location":"UCC-59"}],"instructor":"Y. Kharrat"},"12494":{"subject":"ARABIC","name":"1030","type":"LEC","schedule":[{"start":"2021/9/14 12:30 PM","end":"2021/9/14 2:30 PM","rrule":{"byday":["TU","TH"],"until":"2022/4/1","freq":"WEEKLY"},"location":"UCC-54B"}],"instructor":"Y. Kharrat"},"12495":{"subject":"ARABIC","name":"1035","type":"LEC","schedule":[{"start":"2021/9/14 12:30 PM","end":"2021/9/14 2:30 PM","rrule":{"byday":["TU","TH"],"until":"2022/4/1","freq":"WEEKLY"},"location":"UCC-54B"}],"instructor":"Y. Kharrat"}}