{"7859":{"subject":"INTEGSCI","name":"2001F","type":"TUT","schedule":[{"start":"2021/9/8 12:30 PM","end":"2021/9/8 1:30 PM","rrule":{"byday":["WE"],"until":"2021/12/8","freq":"WEEKLY"},"location":"UCC-56"}],"instructor":"T. Hain"},"7911":{"subject":"INTEGSCI","name":"2002B","type":"TUT","schedule":[{"start":"2022/1/7 12:30 PM","end":"2022/1/7 2:30 PM","rrule":{"byday":["FR"],"until":"2022/4/1","freq":"WEEKLY"},"location":"HSB-11"}],"instructor":""},"7912":{"subject":"INTEGSCI","name":"2002B","type":"TUT","schedule":[{"start":"2022/1/7 2:30 PM","end":"2022/1/7 4:30 PM","rrule":{"byday":["FR"],"until":"2022/4/1","freq":"WEEKLY"},"location":"HSB-9"}],"instructor":""}}