{"3166":{"subject":"MEDBIO","name":"3330F","type":"LAB","schedule":[{"start":"2021/9/10 3:30 PM","end":"2021/9/10 5:30 PM","rrule":{"byday":["FR"],"until":"2021/12/8","freq":"WEEKLY"},"location":"PAB-150"}],"instructor":"A. Samani"},"3190":{"subject":"MEDBIO","name":"3505F","type":"LAB","schedule":[{"start":"2021/9/8 2:30 PM","end":"2021/9/8 4:30 PM","rrule":{"byday":["WE"],"until":"2021/12/8","freq":"WEEKLY"},"location":""}],"instructor":"N. Gelman"},"3191":{"subject":"MEDBIO","name":"3505F","type":"LAB","schedule":[{"start":"2021/9/9 2:30 PM","end":"2021/9/9 4:30 PM","rrule":{"byday":["TH"],"until":"2021/12/8","freq":"WEEKLY"},"location":""}],"instructor":"K. St Lawrence"},"4729":{"subject":"MEDBIO","name":"3507G","type":"LAB","schedule":[{"start":"2022/1/5 2:30 PM","end":"2022/1/5 4:30 PM","rrule":{"byday":["WE"],"until":"2022/4/1","freq":"WEEKLY"},"location":""}],"instructor":""},"4730":{"subject":"MEDBIO","name":"3507G","type":"LAB","schedule":[{"start":"2022/1/6 2:30 PM","end":"2022/1/6 4:30 PM","rrule":{"byday":["TH"],"until":"2022/4/1","freq":"WEEKLY"},"location":""}],"instructor":"D. Goldman"}}