{"8954":{"subject":"MUSIC","name":"2639U","type":"TUT","schedule":[{"start":"2021/9/13 9:30 AM","end":"2021/9/13 10:30 AM","rrule":{"byday":["MO"],"until":"2021/12/8","freq":"WEEKLY"},"location":"TC-202"}],"instructor":""},"8955":{"subject":"MUSIC","name":"2639U","type":"TUT","schedule":[{"start":"2021/9/13 10:30 AM","end":"2021/9/13 11:30 AM","rrule":{"byday":["MO"],"until":"2021/12/8","freq":"WEEKLY"},"location":"MB-140"}],"instructor":""},"8956":{"subject":"MUSIC","name":"2639U","type":"TUT","schedule":[{"start":"2021/9/13 1:30 PM","end":"2021/9/13 2:30 PM","rrule":{"byday":["MO"],"until":"2021/12/8","freq":"WEEKLY"},"location":"TC-204"}],"instructor":""},"8957":{"subject":"MUSIC","name":"2639U","type":"TUT","schedule":[{"start":"2021/9/13 2:30 PM","end":"2021/9/13 3:30 PM","rrule":{"byday":["MO"],"until":"2021/12/8","freq":"WEEKLY"},"location":"MB-140"}],"instructor":""},"8958":{"subject":"MUSIC","name":"2639U","type":"TUT","schedule":[{"start":"2021/9/14 1:30 PM","end":"2021/9/14 2:30 PM","rrule":{"byday":["TU"],"until":"2021/12/8","freq":"WEEKLY"},"location":"TC-305"}],"instructor":""},"8959":{"subject":"MUSIC","name":"2639U","type":"TUT","schedule":[{"start":"2021/9/14 2:30 PM","end":"2021/9/14 3:30 PM","rrule":{"byday":["TU"],"until":"2021/12/8","freq":"WEEKLY"},"location":"MB-140"}],"instructor":""},"8960":{"subject":"MUSIC","name":"2639U","type":"TUT","schedule":[{"start":"2021/9/9 1:30 PM","end":"2021/9/9 2:30 PM","rrule":{"byday":["TH"],"until":"2021/12/8","freq":"WEEKLY"},"location":"TC-305"}],"instructor":""},"8961":{"subject":"MUSIC","name":"2639U","type":"TUT","schedule":[{"start":"2021/9/9 2:30 PM","end":"2021/9/9 3:30 PM","rrule":{"byday":["TH"],"until":"2021/12/8","freq":"WEEKLY"},"location":"TC-305"}],"instructor":""},"8962":{"subject":"MUSIC","name":"2639U","type":"TUT","schedule":[{"start":"2021/9/10 9:30 AM","end":"2021/9/10 10:30 AM","rrule":{"byday":["FR"],"until":"2021/12/8","freq":"WEEKLY"},"location":"TC-201"}],"instructor":""},"8963":{"subject":"MUSIC","name":"2639U","type":"TUT","schedule":[{"start":"2021/9/9 1:30 PM","end":"2021/9/9 2:30 PM","rrule":{"byday":["TH"],"until":"2021/12/8","freq":"WEEKLY"},"location":"TC-204"}],"instructor":""},"8964":{"subject":"MUSIC","name":"2639U","type":"TUT","schedule":[{"start":"2021/9/10 2:30 PM","end":"2021/9/10 3:30 PM","rrule":{"byday":["FR"],"until":"2021/12/8","freq":"WEEKLY"},"location":"MB-140"}],"instructor":""},"8965":{"subject":"MUSIC","name":"2639U","type":"TUT","schedule":[{"start":"2021/9/8 9:30 AM","end":"2021/9/8 10:30 AM","rrule":{"byday":["WE"],"until":"2021/12/8","freq":"WEEKLY"},"location":"TC-204"}],"instructor":""},"8970":{"subject":"MUSIC","name":"2641U","type":"TUT","schedule":[{"start":"2022/1/3 9:30 AM","end":"2022/1/3 10:30 AM","rrule":{"byday":["MO"],"until":"2022/4/1","freq":"WEEKLY"},"location":"TC-201"}],"instructor":""},"8971":{"subject":"MUSIC","name":"2641U","type":"TUT","schedule":[{"start":"2022/1/3 10:30 AM","end":"2022/1/3 11:30 AM","rrule":{"byday":["MO"],"until":"2022/4/1","freq":"WEEKLY"},"location":"TC-202"}],"instructor":""},"8972":{"subject":"MUSIC","name":"2641U","type":"TUT","schedule":[{"start":"2022/1/3 1:30 PM","end":"2022/1/3 2:30 PM","rrule":{"byday":["MO"],"until":"2022/4/1","freq":"WEEKLY"},"location":"TC-305"}],"instructor":""},"8973":{"subject":"MUSIC","name":"2641U","type":"TUT","schedule":[{"start":"2022/1/3 2:30 PM","end":"2022/1/3 3:30 PM","rrule":{"byday":["MO"],"until":"2022/4/1","freq":"WEEKLY"},"location":"MB-140"}],"instructor":""},"8974":{"subject":"MUSIC","name":"2641U","type":"TUT","schedule":[{"start":"2022/1/4 1:30 PM","end":"2022/1/4 2:30 PM","rrule":{"byday":["TU"],"until":"2022/4/1","freq":"WEEKLY"},"location":"TC-305"}],"instructor":""},"8975":{"subject":"MUSIC","name":"2641U","type":"TUT","schedule":[{"start":"2022/1/4 2:30 PM","end":"2022/1/4 3:30 PM","rrule":{"byday":["TU"],"until":"2022/4/1","freq":"WEEKLY"},"location":"MB-140"}],"instructor":""},"8976":{"subject":"MUSIC","name":"2641U","type":"TUT","schedule":[{"start":"2022/1/6 1:30 PM","end":"2022/1/6 2:30 PM","rrule":{"byday":["TH"],"until":"2022/4/1","freq":"WEEKLY"},"location":"TC-305"}],"instructor":""},"8977":{"subject":"MUSIC","name":"2641U","type":"TUT","schedule":[{"start":"2022/1/6 2:30 PM","end":"2022/1/6 3:30 PM","rrule":{"byday":["TH"],"until":"2022/4/1","freq":"WEEKLY"},"location":"TC-305"}],"instructor":""},"8978":{"subject":"MUSIC","name":"2641U","type":"TUT","schedule":[{"start":"2022/1/7 9:30 AM","end":"2022/1/7 10:30 AM","rrule":{"byday":["FR"],"until":"2022/4/1","freq":"WEEKLY"},"location":"TC-201"}],"instructor":""},"8979":{"subject":"MUSIC","name":"2641U","type":"TUT","schedule":[{"start":"2022/1/6 1:30 PM","end":"2022/1/6 2:30 PM","rrule":{"byday":["TH"],"until":"2022/4/1","freq":"WEEKLY"},"location":"TC-201"}],"instructor":""},"8980":{"subject":"MUSIC","name":"2641U","type":"TUT","schedule":[{"start":"2022/1/7 2:30 PM","end":"2022/1/7 3:30 PM","rrule":{"byday":["FR"],"until":"2022/4/1","freq":"WEEKLY"},"location":"MB-140"}],"instructor":""},"8981":{"subject":"MUSIC","name":"2641U","type":"TUT","schedule":[{"start":"2022/1/5 9:30 AM","end":"2022/1/5 10:30 AM","rrule":{"byday":["WE"],"until":"2022/4/1","freq":"WEEKLY"},"location":"TC-201"}],"instructor":""}}