{"1103":{"subject":"PSYCHOL","name":"3891F","type":"LEC","schedule":[{"start":"2021/9/9 2:30 PM","end":"2021/9/9 4:30 PM","rrule":{"byday":["TH"],"until":"2021/12/8","freq":"WEEKLY"},"location":"KC-W164"}],"instructor":"G. Gorman"},"1104":{"subject":"PSYCHOL","name":"3892G","type":"LEC","schedule":[{"start":"2022/1/6 12:30 PM","end":"2022/1/6 2:30 PM","rrule":{"byday":["TH"],"until":"2022/4/1","freq":"WEEKLY"},"location":"KC-FB003"}],"instructor":"C. Roney"},"1252":{"subject":"PSYCHOL","name":"3371F","type":"LEC","schedule":[{"start":"2021/9/9 11:30 AM","end":"2021/9/9 2:30 PM","rrule":{"byday":["TH"],"until":"2021/12/8","freq":"WEEKLY"},"location":"KC-DL114"}],"instructor":"A. Koenig"},"1279":{"subject":"PSYCHOL","name":"3371G","type":"LEC","schedule":[{"start":"2022/1/7 11:30 AM","end":"2022/1/7 2:30 PM","rrule":{"byday":["FR"],"until":"2022/4/1","freq":"WEEKLY"},"location":"KC-FB110"}],"instructor":"A. Koenig"},"1492":{"subject":"PSYCHOL","name":"3313A","type":"LEC","schedule":[{"start":"2021/9/8 8:30 AM","end":"2021/9/8 11:30 AM","rrule":{"byday":["WE"],"until":"2021/12/8","freq":"WEEKLY"},"location":"KC-DL114"}],"instructor":"K. Briggs"},"1555":{"subject":"PSYCHOL","name":"3893F","type":"LEC","schedule":[{"start":"2021/9/9 8:30 AM","end":"2021/9/9 11:30 AM","rrule":{"byday":["TH"],"until":"2021/12/8","freq":"WEEKLY"},"location":"KC-W176"}],"instructor":"C. Roney"},"1728":{"subject":"PSYCHOL","name":"3770G","type":"LEC","schedule":[{"start":"2022/1/3 2:30 PM","end":"2022/1/3 5:30 PM","rrule":{"byday":["MO"],"until":"2022/4/1","freq":"WEEKLY"},"location":"KC-W173"}],"instructor":"C. Roney"},"1749":{"subject":"PSYCHOL","name":"3310G","type":"LEC","schedule":[{"start":"2022/1/6 11:30 AM","end":"2022/1/6 2:30 PM","rrule":{"byday":["TH"],"until":"2022/4/1","freq":"WEEKLY"},"location":"KC-W147"}],"instructor":"T. Zdyb"},"1783":{"subject":"PSYCHOL","name":"3781F","type":"LEC","schedule":[{"start":"2021/9/14 11:30 AM","end":"2021/9/14 2:30 PM","rrule":{"byday":["TU"],"until":"2021/12/8","freq":"WEEKLY"},"location":"KC-BH107"}],"instructor":"W. Ellis"},"1784":{"subject":"PSYCHOL","name":"3840G","type":"LEC","schedule":[{"start":"2022/1/7 11:30 AM","end":"2022/1/7 2:30 PM","rrule":{"byday":["FR"],"until":"2022/4/1","freq":"WEEKLY"},"location":"KC-W175"}],"instructor":"W. Ellis"},"1811":{"subject":"PSYCHOL","name":"3320F","type":"LEC","schedule":[{"start":"2021/9/10 11:30 AM","end":"2021/9/10 2:30 PM","rrule":{"byday":["FR"],"until":"2021/12/8","freq":"WEEKLY"},"location":"KC-W045"}],"instructor":"K. Turnbull"},"1884":{"subject":"PSYCHOL","name":"3830F","type":"LEC","schedule":[{"start":"2021/9/8 10:30 AM","end":"2021/9/8 12:30 PM","rrule":{"byday":["WE"],"until":"2021/12/8","freq":"WEEKLY"},"location":""},{"start":"2021/9/10 11:30 AM","end":"2021/9/10 12:30 PM","rrule":{"byday":["FR"],"until":"2021/12/8","freq":"WEEKLY"},"location":""}],"instructor":"S. Hessels"},"1953":{"subject":"PSYCHOL","name":"3227B","type":"LEC","schedule":[{"start":"2022/1/3 6:30 PM","end":"2022/1/3 9:30 PM","rrule":{"byday":["MO"],"until":"2022/4/1","freq":"WEEKLY"},"location":"HC-W101"}],"instructor":"J. Hoshooley"},"1972":{"subject":"PSYCHOL","name":"3830G","type":"LEC","schedule":[{"start":"2022/1/5 10:30 AM","end":"2022/1/5 12:30 PM","rrule":{"byday":["WE"],"until":"2022/4/1","freq":"WEEKLY"},"location":""},{"start":"2022/1/7 11:30 AM","end":"2022/1/7 12:30 PM","rrule":{"byday":["FR"],"until":"2022/4/1","freq":"WEEKLY"},"location":""}],"instructor":"S. Hessels"},"2135":{"subject":"PSYCHOL","name":"3696G","type":"LEC","schedule":[{"start":"2022/1/4 12:30 PM","end":"2022/1/4 2:30 PM","rrule":{"byday":["TU"],"until":"2022/4/1","freq":"WEEKLY"},"location":"HC-H119"}],"instructor":"I. Cheung"},"2221":{"subject":"PSYCHOL","name":"3830G","type":"LEC","schedule":[{"start":"2022/1/5 1:30 PM","end":"2022/1/5 2:30 PM","rrule":{"byday":["WE"],"until":"2022/4/1","freq":"WEEKLY"},"location":""},{"start":"2022/1/7 1:30 PM","end":"2022/1/7 3:30 PM","rrule":{"byday":["FR"],"until":"2022/4/1","freq":"WEEKLY"},"location":""}],"instructor":"S. Hessels"},"2229":{"subject":"PSYCHOL","name":"3726F","type":"LEC","schedule":[{"start":"2021/9/14 12:30 PM","end":"2021/9/14 2:30 PM","rrule":{"byday":["TU","TH"],"until":"2021/12/8","freq":"WEEKLY"},"location":"HC-W17"}],"instructor":"I. Cheung"},"2292":{"subject":"PSYCHOL","name":"3722G","type":"LEC","schedule":[{"start":"2022/1/6 6:30 PM","end":"2022/1/6 9:30 PM","rrule":{"byday":["TH"],"until":"2022/4/1","freq":"WEEKLY"},"location":"HC-W17"}],"instructor":"G. Gorman"},"2415":{"subject":"PSYCHOL","name":"3222G","type":"LEC","schedule":[{"start":"2022/1/7 8:30 AM","end":"2022/1/7 11:30 AM","rrule":{"byday":["FR"],"until":"2022/4/1","freq":"WEEKLY"},"location":"HC-W108"}],"instructor":"D. Quinlan"},"2416":{"subject":"PSYCHOL","name":"3227A","type":"LEC","schedule":[{"start":"2021/9/13 6:30 PM","end":"2021/9/13 9:30 PM","rrule":{"byday":["MO"],"until":"2021/12/8","freq":"WEEKLY"},"location":"HC-H220"}],"instructor":"J. Hoshooley"},"2507":{"subject":"PSYCHOL","name":"3313A","type":"LEC","schedule":[{"start":"2021/9/14 11:30 AM","end":"2021/9/14 2:30 PM","rrule":{"byday":["TU"],"until":"2021/12/8","freq":"WEEKLY"},"location":"BR-303"}],"instructor":"L. Janes"},"2527":{"subject":"PSYCHOL","name":"3434E","type":"LEC","schedule":[{"start":"2021/9/13","end":"2021/9/13","rrule":{"byday":["MO","TU","WE","TH","FR"],"until":"2022/4/1","freq":"WEEKLY"},"location":""}],"instructor":"K. McKeown"},"2561":{"subject":"PSYCHOL","name":"3800F","type":"LEC","schedule":[{"start":"2021/9/9 9:30 AM","end":"2021/9/9 11:30 AM","rrule":{"byday":["TH"],"until":"2021/12/8","freq":"WEEKLY"},"location":"BR-2013"}],"instructor":"J. Sutton"},"2571":{"subject":"PSYCHOL","name":"3311","type":"LEC","schedule":[{"start":"2021/9/13 2:30 PM","end":"2021/9/13 5:30 PM","rrule":{"byday":["MO"],"until":"2022/4/1","freq":"WEEKLY"},"location":"BR-UH250"}],"instructor":"R. Shugar"},"2616":{"subject":"PSYCHOL","name":"3215G","type":"LEC","schedule":[{"start":"2022/1/4 11:30 AM","end":"2022/1/4 2:30 PM","rrule":{"byday":["TU"],"until":"2022/4/1","freq":"WEEKLY"},"location":"BR-UH250"}],"instructor":"J. Hoshooley"},"2637":{"subject":"PSYCHOL","name":"3313B","type":"LEC","schedule":[{"start":"2022/1/6 2:30 PM","end":"2022/1/6 5:30 PM","rrule":{"byday":["TH"],"until":"2022/4/1","freq":"WEEKLY"},"location":"BR-203"}],"instructor":"J. Campbell"},"2744":{"subject":"PSYCHOL","name":"3721G","type":"LEC","schedule":[{"start":"2022/1/5 11:30 AM","end":"2022/1/5 2:30 PM","rrule":{"byday":["WE"],"until":"2022/4/1","freq":"WEEKLY"},"location":"BR-135"}],"instructor":"L. Janes"},"2897":{"subject":"PSYCHOL","name":"3450F","type":"LEC","schedule":[{"start":"2021/9/9 9:30 AM","end":"2021/9/9 11:30 AM","rrule":{"byday":["TH"],"until":"2021/12/8","freq":"WEEKLY"},"location":"HC-W101"}],"instructor":"S. Chiarella"},"3007":{"subject":"PSYCHOL","name":"3260G","type":"LEC","schedule":[{"start":"2022/1/6 2:30 PM","end":"2022/1/6 5:30 PM","rrule":{"byday":["TH"],"until":"2022/4/1","freq":"WEEKLY"},"location":"KC-LH105C"}],"instructor":"L. Norton"},"3008":{"subject":"PSYCHOL","name":"3330F","type":"LEC","schedule":[{"start":"2021/9/13 6:30 PM","end":"2021/9/13 9:30 PM","rrule":{"byday":["MO"],"until":"2021/12/8","freq":"WEEKLY"},"location":"KC-W147"}],"instructor":"N. Lapshina"},"3011":{"subject":"PSYCHOL","name":"3781G","type":"LEC","schedule":[{"start":"2022/1/4 2:30 PM","end":"2022/1/4 5:30 PM","rrule":{"byday":["TU"],"until":"2022/4/1","freq":"WEEKLY"},"location":"KC-FB003"}],"instructor":"W. Ellis"},"3012":{"subject":"PSYCHOL","name":"3891G","type":"LEC","schedule":[{"start":"2022/1/4 8:30 AM","end":"2022/1/4 10:30 AM","rrule":{"byday":["TU"],"until":"2022/4/1","freq":"WEEKLY"},"location":"KC-BH109"}],"instructor":"N. Lapshina"},"3014":{"subject":"PSYCHOL","name":"3892F","type":"LEC","schedule":[{"start":"2021/9/8 10:30 AM","end":"2021/9/8 12:30 PM","rrule":{"byday":["WE"],"until":"2021/12/8","freq":"WEEKLY"},"location":"KC-W164"}],"instructor":"C. Roney"},"3016":{"subject":"PSYCHOL","name":"3893G","type":"LEC","schedule":[{"start":"2022/1/4 8:30 AM","end":"2022/1/4 11:30 AM","rrule":{"byday":["TU"],"until":"2022/4/1","freq":"WEEKLY"},"location":"KC-DL114"}],"instructor":"C. Roney"},"3017":{"subject":"PSYCHOL","name":"3992G","type":"LEC","schedule":[{"start":"2022/1/5 8:30 AM","end":"2022/1/5 11:30 AM","rrule":{"byday":["WE"],"until":"2022/4/1","freq":"WEEKLY"},"location":"KC-W173"}],"instructor":"L. Rosen"},"3262":{"subject":"PSYCHOL","name":"3800F","type":"LEC","schedule":[{"start":"2021/9/8 9:30 AM","end":"2021/9/8 11:30 AM","rrule":{"byday":["WE"],"until":"2021/12/8","freq":"WEEKLY"},"location":"VAC-100"}],"instructor":"R. Stevenson"},"3264":{"subject":"PSYCHOL","name":"3800G","type":"LEC","schedule":[{"start":"2022/1/4 2:30 PM","end":"2022/1/4 4:30 PM","rrule":{"byday":["TU"],"until":"2022/4/1","freq":"WEEKLY"},"location":"WIRB-1170"}],"instructor":"R. Stevenson"},"4421":{"subject":"PSYCHOL","name":"3224A","type":"LEC","schedule":[{"start":"2021/9/13","end":"2021/9/13","rrule":{"byday":["MO","TU","WE","TH","FR"],"until":"2021/12/8","freq":"WEEKLY"},"location":""}],"instructor":"L. Batterink"},"4601":{"subject":"PSYCHOL","name":"3720G","type":"LEC","schedule":[{"start":"2022/1/4 2:30 PM","end":"2022/1/4 5:30 PM","rrule":{"byday":["TU"],"until":"2022/4/1","freq":"WEEKLY"},"location":"SSC-3014"}],"instructor":"A. Benson"},"4602":{"subject":"PSYCHOL","name":"3580F","type":"LEC","schedule":[{"start":"2021/9/14 9:30 AM","end":"2021/9/14 11:30 AM","rrule":{"byday":["TU","TH"],"until":"2021/12/8","freq":"WEEKLY"},"location":"UC-3225"}],"instructor":"R. Goffin"},"4847":{"subject":"PSYCHOL","name":"3485F","type":"LEC","schedule":[{"start":"2021/9/14 9:30 AM","end":"2021/9/14 11:30 AM","rrule":{"byday":["TU"],"until":"2021/12/8","freq":"WEEKLY"},"location":"WIRB-1130"}],"instructor":"B. Morton"},"5324":{"subject":"PSYCHOL","name":"3723G","type":"LEC","schedule":[{"start":"2022/1/3 7:00 PM","end":"2022/1/3 9:00 PM","rrule":{"byday":["MO"],"until":"2022/4/1","freq":"WEEKLY"},"location":"UCC-37"}],"instructor":"C. Isaacs"},"5418":{"subject":"PSYCHOL","name":"3130A","type":"LEC","schedule":[{"start":"2021/9/13","end":"2021/9/13","rrule":{"byday":["MO","TU","WE","TH","FR"],"until":"2021/12/8","freq":"WEEKLY"},"location":""}],"instructor":"A. Ruiz Pardo"},"5837":{"subject":"PSYCHOL","name":"3315E","type":"LEC","schedule":[{"start":"2021/9/14 2:30 PM","end":"2021/9/14 4:30 PM","rrule":{"byday":["TU"],"until":"2022/4/1","freq":"WEEKLY"},"location":"KB-K103"}],"instructor":"R. Hinson"},"5851":{"subject":"PSYCHOL","name":"3780G","type":"LEC","schedule":[{"start":"2022/1/5 9:30 AM","end":"2022/1/5 11:30 AM","rrule":{"byday":["WE"],"until":"2022/4/1","freq":"WEEKLY"},"location":"UC-3225"}],"instructor":"J. Sakaluk"},"6121":{"subject":"PSYCHOL","name":"3720F","type":"LEC","schedule":[{"start":"2021/9/13","end":"2021/9/13","rrule":{"byday":["MO","TU","WE","TH","FR"],"until":"2021/12/8","freq":"WEEKLY"},"location":""}],"instructor":"G. Haynes"},"6301":{"subject":"PSYCHOL","name":"3130B","type":"LEC","schedule":[{"start":"2022/1/4 9:30 AM","end":"2022/1/4 12:30 PM","rrule":{"byday":["TU"],"until":"2022/4/1","freq":"WEEKLY"},"location":"3M-3250"}],"instructor":"J. Minda"},"6302":{"subject":"PSYCHOL","name":"3139B","type":"LEC","schedule":[{"start":"2022/1/6 3:30 PM","end":"2022/1/6 6:30 PM","rrule":{"byday":["TH"],"until":"2022/4/1","freq":"WEEKLY"},"location":"UCC-67"}],"instructor":"M. Mur"},"6303":{"subject":"PSYCHOL","name":"3224B","type":"LEC","schedule":[{"start":"2022/1/3","end":"2022/1/3","rrule":{"byday":["MO","TU","WE","TH","FR"],"until":"2022/4/1","freq":"WEEKLY"},"location":""}],"instructor":"L. Batterink"},"6422":{"subject":"PSYCHOL","name":"3140F","type":"LEC","schedule":[{"start":"2021/9/13","end":"2021/9/13","rrule":{"byday":["MO","TU","WE","TH","FR"],"until":"2021/12/8","freq":"WEEKLY"},"location":""}],"instructor":"D. Jared"},"7009":{"subject":"PSYCHOL","name":"3221G","type":"LEC","schedule":[{"start":"2022/1/6 9:30 AM","end":"2022/1/6 12:30 PM","rrule":{"byday":["TH"],"until":"2022/4/1","freq":"WEEKLY"},"location":"UCC-54A"}],"instructor":"C. Strang"},"7310":{"subject":"PSYCHOL","name":"3996F","type":"LEC","schedule":[{"start":"2021/9/13","end":"2021/9/13","rrule":{"byday":["MO","TU","WE","TH","FR"],"until":"2021/12/8","freq":"WEEKLY"},"location":""}],"instructor":"L. Campbell"},"7311":{"subject":"PSYCHOL","name":"3997G","type":"LEC","schedule":[{"start":"2022/1/3","end":"2022/1/3","rrule":{"byday":["MO","TU","WE","TH","FR"],"until":"2022/4/1","freq":"WEEKLY"},"location":""}],"instructor":"L. Campbell"},"7318":{"subject":"PSYCHOL","name":"3317E","type":"LEC","schedule":[{"start":"2021/9/8 1:30 PM","end":"2021/9/8 4:30 PM","rrule":{"byday":["WE"],"until":"2022/4/1","freq":"WEEKLY"},"location":"WH-20E"}],"instructor":"L. Swartzman"},"7611":{"subject":"PSYCHOL","name":"3724F","type":"LEC","schedule":[{"start":"2021/9/14 12:30 PM","end":"2021/9/14 2:30 PM","rrule":{"byday":["TU"],"until":"2021/12/8","freq":"WEEKLY"},"location":"SSC-2032"}],"instructor":"R. Koessler"},"7775":{"subject":"PSYCHOL","name":"3185F","type":"LEC","schedule":[{"start":"2021/9/13 4:30 PM","end":"2021/9/13 6:30 PM","rrule":{"byday":["MO","WE"],"until":"2021/12/8","freq":"WEEKLY"},"location":"SH-3307"}],"instructor":"S. Yasmin"},"7776":{"subject":"PSYCHOL","name":"3185G","type":"LEC","schedule":[{"start":"2022/1/3 4:30 PM","end":"2022/1/3 6:30 PM","rrule":{"byday":["MO","WE"],"until":"2022/4/1","freq":"WEEKLY"},"location":"UCC-59"}],"instructor":"S. Yasmin"},"7777":{"subject":"PSYCHOL","name":"3138G","type":"LEC","schedule":[{"start":"2022/1/6 9:30 AM","end":"2022/1/6 12:30 PM","rrule":{"byday":["TH"],"until":"2022/4/1","freq":"WEEKLY"},"location":"UCC-54B"}],"instructor":"S. Kohler"},"7778":{"subject":"PSYCHOL","name":"3141F","type":"LEC","schedule":[{"start":"2021/9/13 2:30 PM","end":"2021/9/13 4:30 PM","rrule":{"byday":["MO"],"until":"2021/12/8","freq":"WEEKLY"},"location":"UC-3225"},{"start":"2021/9/8 2:30 PM","end":"2021/9/8 3:30 PM","rrule":{"byday":["WE"],"until":"2021/12/8","freq":"WEEKLY"},"location":"UC-3225"}],"instructor":"N. Noonan"},"7874":{"subject":"PSYCHOL","name":"3316G","type":"LEC","schedule":[{"start":"2022/1/6 9:30 AM","end":"2022/1/6 11:30 AM","rrule":{"byday":["TH"],"until":"2022/4/1","freq":"WEEKLY"},"location":"UCC-61"}],"instructor":"P. Frewen"},"8146":{"subject":"PSYCHOL","name":"3301F","type":"LEC","schedule":[{"start":"2021/9/14 9:30 AM","end":"2021/9/14 12:30 PM","rrule":{"byday":["TU"],"until":"2021/12/8","freq":"WEEKLY"},"location":"UCC-61"}],"instructor":"E. Kaufman"},"8882":{"subject":"PSYCHOL","name":"3442F","type":"LEC","schedule":[{"start":"2021/9/9 3:30 PM","end":"2021/9/9 6:30 PM","rrule":{"byday":["TH"],"until":"2021/12/8","freq":"WEEKLY"},"location":"WIRB-1170"}],"instructor":"D. Ansari"},"9165":{"subject":"PSYCHOL","name":"3228B","type":"LEC","schedule":[{"start":"2022/1/3","end":"2022/1/3","rrule":{"byday":["MO","TU","WE","TH","FR"],"until":"2022/4/1","freq":"WEEKLY"},"location":""}],"instructor":"S. MacDougall-Shackleton"},"9391":{"subject":"PSYCHOL","name":"3301G","type":"LEC","schedule":[{"start":"2022/1/4 9:30 AM","end":"2022/1/4 12:30 PM","rrule":{"byday":["TU"],"until":"2022/4/1","freq":"WEEKLY"},"location":"UCC-54B"}],"instructor":"A. Newton"},"9393":{"subject":"PSYCHOL","name":"3950G","type":"LEC","schedule":[{"start":"2022/1/5 12:30 PM","end":"2022/1/5 3:30 PM","rrule":{"byday":["WE"],"until":"2022/4/1","freq":"WEEKLY"},"location":"SSC-3018"}],"instructor":"K. Macpherson"},"9394":{"subject":"PSYCHOL","name":"3316F","type":"LEC","schedule":[{"start":"2021/9/9 9:30 AM","end":"2021/9/9 11:30 AM","rrule":{"byday":["TH"],"until":"2021/12/8","freq":"WEEKLY"},"location":"SSC-3024"}],"instructor":"P. Frewen"},"9679":{"subject":"PSYCHOL","name":"3895E","type":"LEC","schedule":[{"start":"2021/9/14 1:30 PM","end":"2021/9/14 4:30 PM","rrule":{"byday":["TU"],"until":"2022/4/1","freq":"WEEKLY"},"location":"WH-20E"}],"instructor":"L. Swartzman"},"10128":{"subject":"PSYCHOL","name":"3774F","type":"LEC","schedule":[{"start":"2021/9/13","end":"2021/9/13","rrule":{"byday":["MO","TU","WE","TH","FR"],"until":"2021/12/8","freq":"WEEKLY"},"location":""}],"instructor":"M. Everest"},"10129":{"subject":"PSYCHOL","name":"3375F","type":"LEC","schedule":[{"start":"2021/9/14 4:30 PM","end":"2021/9/14 7:30 PM","rrule":{"byday":["TU"],"until":"2021/12/8","freq":"WEEKLY"},"location":"BR-2013"}],"instructor":"R. Shugar"},"10132":{"subject":"PSYCHOL","name":"3254B","type":"LEC","schedule":[{"start":"2022/1/3 8:30 AM","end":"2022/1/3 11:30 AM","rrule":{"byday":["MO"],"until":"2022/4/1","freq":"WEEKLY"},"location":"BR-UH27"}],"instructor":"C. Tenk"},"10133":{"subject":"PSYCHOL","name":"3209F","type":"LEC","schedule":[{"start":"2021/9/13 2:30 PM","end":"2021/9/13 5:30 PM","rrule":{"byday":["MO"],"until":"2021/12/8","freq":"WEEKLY"},"location":"BR-19"}],"instructor":"J. Hoshooley"},"10197":{"subject":"PSYCHOL","name":"3994F","type":"LEC","schedule":[{"start":"2021/9/13 2:30 PM","end":"2021/9/13 5:30 PM","rrule":{"byday":["MO"],"until":"2021/12/8","freq":"WEEKLY"},"location":"KC-W173"}],"instructor":"S. Hessels"},"10550":{"subject":"PSYCHOL","name":"3184F","type":"LEC","schedule":[{"start":"2021/9/13 10:30 AM","end":"2021/9/13 12:30 PM","rrule":{"byday":["MO","WE"],"until":"2021/12/8","freq":"WEEKLY"},"location":"UC-3225"}],"instructor":"L. Batterink"},"10551":{"subject":"PSYCHOL","name":"3312G","type":"LEC","schedule":[{"start":"2022/1/3 12:30 PM","end":"2022/1/3 3:30 PM","rrule":{"byday":["MO"],"until":"2022/4/1","freq":"WEEKLY"},"location":"SSC-2028"}],"instructor":"E. Collins"},"10552":{"subject":"PSYCHOL","name":"3441G","type":"LEC","schedule":[{"start":"2022/1/4 12:30 PM","end":"2022/1/4 3:30 PM","rrule":{"byday":["TU"],"until":"2022/4/1","freq":"WEEKLY"},"location":"UC-2105"}],"instructor":"J. Furlano"},"10561":{"subject":"PSYCHOL","name":"3225A","type":"LEC","schedule":[{"start":"2021/9/8 11:30 AM","end":"2021/9/8 2:30 PM","rrule":{"byday":["WE"],"until":"2021/12/8","freq":"WEEKLY"},"location":"SSC-2028"}],"instructor":"A. Pierias"},"10562":{"subject":"PSYCHOL","name":"3230F","type":"LEC","schedule":[{"start":"2021/9/14 1:30 PM","end":"2021/9/14 4:30 PM","rrule":{"byday":["TU"],"until":"2021/12/8","freq":"WEEKLY"},"location":"UCC-59"}],"instructor":"J. Grahn"},"11099":{"subject":"PSYCHOL","name":"3610G","type":"LEC","schedule":[{"start":"2022/1/5 12:30 PM","end":"2022/1/5 3:30 PM","rrule":{"byday":["WE"],"until":"2022/4/1","freq":"WEEKLY"},"location":"SSC-2020"}],"instructor":"R. Goffin"},"11259":{"subject":"PSYCHOL","name":"3995G","type":"LEC","schedule":[{"start":"2022/1/6 8:30 AM","end":"2022/1/6 11:30 AM","rrule":{"byday":["TH"],"until":"2022/4/1","freq":"WEEKLY"},"location":"KC-FB110"}],"instructor":"M. Morrison"},"11432":{"subject":"PSYCHOL","name":"3318G","type":"LEC","schedule":[{"start":"2022/1/3","end":"2022/1/3","rrule":{"byday":["MO","TU","WE","TH","FR"],"until":"2022/4/1","freq":"WEEKLY"},"location":""}],"instructor":"M. Everest"},"11436":{"subject":"PSYCHOL","name":"3330F","type":"LEC","schedule":[{"start":"2021/9/13","end":"2021/9/13","rrule":{"byday":["MO","TU","WE","TH","FR"],"until":"2021/12/8","freq":"WEEKLY"},"location":""}],"instructor":"M. Everest"},"11685":{"subject":"PSYCHOL","name":"3950F","type":"LEC","schedule":[{"start":"2021/9/14 6:30 PM","end":"2021/9/14 9:30 PM","rrule":{"byday":["TU"],"until":"2021/12/8","freq":"WEEKLY"},"location":"HC-W106"}],"instructor":"C. TsangD. van Tol"},"12560":{"subject":"PSYCHOL","name":"3992F","type":"LEC","schedule":[{"start":"2021/9/13 8:30 AM","end":"2021/9/13 11:30 AM","rrule":{"byday":["MO"],"until":"2021/12/8","freq":"WEEKLY"},"location":"KC-W175"}],"instructor":"L. Rosen"},"12762":{"subject":"PSYCHOL","name":"3993G","type":"LEC","schedule":[{"start":"2022/1/4 2:30 PM","end":"2022/1/4 5:30 PM","rrule":{"byday":["TU"],"until":"2022/4/1","freq":"WEEKLY"},"location":"KC-DL114"}],"instructor":"M. Penner-Wilger"}}