{"1132":{"subject":"SPANISH","name":"1030","type":"LEC","schedule":[{"start":"undefined 11:30 AM","end":"undefined 12:30 PM","rrule":{"byday":[null],"until":"2022/4/1","freq":"WEEKLY"}}],"location":"KC-W143","instructor":"S. Brooks<br>"},"2544":{"subject":"SPANISH","name":"1030","type":"LEC","schedule":[{"start":"2021/9/8 6:30 PM","end":"2021/9/8 9:30 PM","rrule":{"byday":["WE"],"until":"2022/4/1","freq":"WEEKLY"}}],"location":"BR-203","instructor":"S. Brooks<br>"},"3146":{"subject":"SPANISH","name":"1030","type":"LEC","schedule":[{"start":"undefined 10:30 AM","end":"undefined 11:30 AM","rrule":{"byday":[null],"until":"2022/4/1","freq":"WEEKLY"}}],"location":"KC-W143","instructor":"S. Brooks<br>"},"3612":{"subject":"SPANISH","name":"1030","type":"LEC","schedule":[{"start":"2021/9/13 10:30 AM","end":"2021/9/13 11:30 AM","rrule":{"byday":["MO","WE","FR"],"until":"2022/4/1","freq":"WEEKLY"}}],"location":"WIRB-1170","instructor":"A. Devo Colis<br>"},"3613":{"subject":"SPANISH","name":"1030","type":"LEC","schedule":[{"start":"2021/9/13 11:30 AM","end":"2021/9/13 1:30 PM","rrule":{"byday":["MO"],"until":"2022/4/1","freq":"WEEKLY"}},{"start":"2021/9/8 11:30 AM","end":"2021/9/8 12:30 PM","rrule":{"byday":["WE"],"until":"2022/4/1","freq":"WEEKLY"}}],"location":"WIRB-1170","instructor":"A. Devo Colis<br>"},"3614":{"subject":"SPANISH","name":"1030","type":"LEC","schedule":[{"start":"2021/9/13 12:30 PM","end":"2021/9/13 2:30 PM","rrule":{"byday":["MO"],"until":"2022/4/1","freq":"WEEKLY"}},{"start":"2021/9/8 12:30 PM","end":"2021/9/8 1:30 PM","rrule":{"byday":["WE"],"until":"2022/4/1","freq":"WEEKLY"}}],"location":"SH-3317","instructor":"A. Devo Colis<br>"},"3616":{"subject":"SPANISH","name":"1030","type":"LEC","schedule":[{"start":"2021/9/13 2:30 PM","end":"2021/9/13 4:30 PM","rrule":{"byday":["MO"],"until":"2022/4/1","freq":"WEEKLY"}},{"start":"2021/9/8 2:30 PM","end":"2021/9/8 3:30 PM","rrule":{"byday":["WE"],"until":"2022/4/1","freq":"WEEKLY"}}],"location":"SH-3307","instructor":"A. Devo Colis<br>"},"3617":{"subject":"SPANISH","name":"1030","type":"LEC","schedule":[{"start":"2021/9/13 3:30 PM","end":"2021/9/13 5:30 PM","rrule":{"byday":["MO"],"until":"2022/4/1","freq":"WEEKLY"}},{"start":"2021/9/8 3:30 PM","end":"2021/9/8 4:30 PM","rrule":{"byday":["WE"],"until":"2022/4/1","freq":"WEEKLY"}}],"location":"MC-105B","instructor":"A. Devo Colis<br>"},"3724":{"subject":"SPANISH","name":"1030","type":"LEC","schedule":[{"start":"2021/9/14 9:30 AM","end":"2021/9/14 11:30 AM","rrule":{"byday":["TU"],"until":"2022/4/1","freq":"WEEKLY"}},{"start":"2021/9/9 9:30 AM","end":"2021/9/9 10:30 AM","rrule":{"byday":["TH"],"until":"2022/4/1","freq":"WEEKLY"}}],"location":"TC-342","instructor":"A. Devo Colis<br>"},"3725":{"subject":"SPANISH","name":"1030","type":"LEC","schedule":[{"start":"2021/9/14 10:30 AM","end":"2021/9/14 12:30 PM","rrule":{"byday":["TU"],"until":"2022/4/1","freq":"WEEKLY"}},{"start":"2021/9/9 10:30 AM","end":"2021/9/9 11:30 AM","rrule":{"byday":["TH"],"until":"2022/4/1","freq":"WEEKLY"}}],"location":"UCC-59","instructor":"A. Devo Colis<br>"},"3777":{"subject":"SPANISH","name":"1030","type":"LEC","schedule":[{"start":"2021/9/13 10:30 AM","end":"2021/9/13 12:30 PM","rrule":{"byday":["MO"],"until":"2022/4/1","freq":"WEEKLY"}},{"start":"2021/9/8 10:30 AM","end":"2021/9/8 11:30 AM","rrule":{"byday":["WE"],"until":"2022/4/1","freq":"WEEKLY"}}],"location":"PAB-34","instructor":"A. Devo Colis<br>"},"3845":{"subject":"SPANISH","name":"1030","type":"LEC","schedule":[{"start":"2021/9/14 11:30 AM","end":"2021/9/14 1:30 PM","rrule":{"byday":["TU"],"until":"2022/4/1","freq":"WEEKLY"}},{"start":"2021/9/9 11:30 AM","end":"2021/9/9 12:30 PM","rrule":{"byday":["TH"],"until":"2022/4/1","freq":"WEEKLY"}}],"location":"FNB-1200","instructor":"A. Devo Colis<br>"},"3968":{"subject":"SPANISH","name":"1030","type":"LEC","schedule":[{"start":"2021/9/14 2:30 PM","end":"2021/9/14 4:30 PM","rrule":{"byday":["TU"],"until":"2022/4/1","freq":"WEEKLY"}},{"start":"2021/9/9 2:30 PM","end":"2021/9/9 3:30 PM","rrule":{"byday":["TH"],"until":"2022/4/1","freq":"WEEKLY"}}],"location":"MC-105B","instructor":"A. Devo Colis<br>"},"5425":{"subject":"SPANISH","name":"1030","type":"LEC","schedule":[{"start":"2021/9/14 4:30 PM","end":"2021/9/14 6:30 PM","rrule":{"byday":["TU"],"until":"2022/4/1","freq":"WEEKLY"}},{"start":"2021/9/9 4:30 PM","end":"2021/9/9 5:30 PM","rrule":{"byday":["TH"],"until":"2022/4/1","freq":"WEEKLY"}}],"location":"SH-2317","instructor":"A. Devo Colis<br>"},"7808":{"subject":"SPANISH","name":"1030","type":"LEC","schedule":[{"start":"2021/9/14 6:30 PM","end":"2021/9/14 9:30 PM","rrule":{"byday":["TU"],"until":"2022/4/1","freq":"WEEKLY"}}],"location":"UC-3220","instructor":"A. Devo Colis<br>"},"7815":{"subject":"SPANISH","name":"1030","type":"LEC","schedule":[{"start":"2021/9/14 12:30 PM","end":"2021/9/14 2:30 PM","rrule":{"byday":["TU"],"until":"2022/4/1","freq":"WEEKLY"}},{"start":"2021/9/9 12:30 PM","end":"2021/9/9 1:30 PM","rrule":{"byday":["TH"],"until":"2022/4/1","freq":"WEEKLY"}}],"location":"SSC-3024","instructor":"A. Devo Colis<br>"},"8604":{"subject":"SPANISH","name":"1030","type":"LEC","schedule":[{"start":"2021/9/13 9:30 AM","end":"2021/9/13 11:30 AM","rrule":{"byday":["MO"],"until":"2022/4/1","freq":"WEEKLY"}},{"start":"2021/9/8 9:30 AM","end":"2021/9/8 10:30 AM","rrule":{"byday":["WE"],"until":"2022/4/1","freq":"WEEKLY"}}],"location":"AHB-1B04","instructor":"A. Devo Colis<br>"},"8934":{"subject":"SPANISH","name":"1030","type":"LEC","schedule":[{"start":"2021/9/13","end":"2021/9/13","rrule":{"byday":["MO","TU","WE","TH","FR"],"until":"2022/4/1","freq":"WEEKLY"}}],"location":"","instructor":"A. Devo Colis<br>"}}